pybomb/__init__.py
pybomb/clients/__init__.py
pybomb/clients/base/__init__.py
pybomb/clients/base/client.py
pybomb/clients/base/fetch_client.py
pybomb/clients/base/search_client.py
pybomb/clients/game_client.py
pybomb/clients/games_client.py
pybomb/clients/platforms_client.py
pybomb/exceptions.py
pybomb/factory.py
pybomb/py.typed
pybomb/response.py
pybomb-0.4.0.dist-info/WHEEL
pybomb-0.4.0.dist-info/METADATA
pybomb-0.4.0.dist-info/RECORD
