Metadata-Version: 2.1
Name: pybomb
Version: 0.4.0
Summary: Simple clients for the Giant Bomb API.
Home-page: https://github.com/steveYeah/PyBomb
License: MIT
Keywords: giantbomb,giant,bomb,game,api,client
Author: steveYeah
Author-email: hutchinsteve@gmail.com
Requires-Python: >=3.6.1,<4.0.0
Classifier: License :: OSI Approved :: MIT License
Classifier: Programming Language :: Python :: 3
Classifier: Programming Language :: Python :: 3.7
Classifier: Programming Language :: Python :: 3.8
Requires-Dist: importlib_metadata (>=1.7.0,<2.0.0); python_version < "3.8"
Requires-Dist: requests (>=2.19.0,<3.0.0)
Project-URL: Documentation, https://pybomb.readthedocs.io/
Project-URL: Repository, https://github.com/steveYeah/PyBomb
